imdump/__main__.py
imdump/fire.py
impeek/__main__.py
impeek/fire.py
impeek-0.0.9.dist-info/LICENSE
impeek-0.0.9.dist-info/METADATA
impeek-0.0.9.dist-info/WHEEL
impeek-0.0.9.dist-info/top_level.txt
impeek-0.0.9.dist-info/RECORD
